{
  "candidate name": "Barbara Bry",
  "description": "Councilmember/ Businesswoman",
  "website": "https://barbarabry.com",
  "raised vs spent": [
    {
      "Raised": "1869012",
      "Spent": "2523724",
      "Donors": "2135",
      "Average Donor": "667"
    }
  ],
  "by industry": [
    {
      "industry 1": [
        "Retired",
        "458203",
        "25"
      ],
      "industry 2": [
        "Councilmember",
        "120000",
        "6"
      ],
      "industry 3": [
        "Attorney",
        "114644",
        "6"
      ],
      "industry 4": [
        "Chief Executive Officer",
        "99473",
        "5"
      ],
      "industry 5": [
        "Not Employed",
        "88663",
        "5"
      ]
    }
  ],
  "in vs out district": [
    {
      "in": "1750417",
      "out": "118594"
    }
  ],
  "oppose": "553407",
  "support": "474323",
  "committee name": "Barbara Bry for San Diego Mayor 2020",
  "first": "Barbara",
  "last": "Bry",
  "in general": true
}
